faceverification/FaceVerification.py
faceverification/__init__.py
faceverification-1.0.dist-info/LICENSE.txt
faceverification-1.0.dist-info/METADATA
faceverification-1.0.dist-info/WHEEL
faceverification-1.0.dist-info/top_level.txt
faceverification-1.0.dist-info/RECORD
